qdk/__init__.py
qdk/exceptions.py
qdk/functions.py
qdk/main.py
qdk/methods.py
qdk/tests/__init__.py
qdk/tests/test_core.py
qdk/tests/test_functions.py
qdk/tests/test_main.py
qodex_dk-0.28.dist-info/LICENSE
qodex_dk-0.28.dist-info/METADATA
qodex_dk-0.28.dist-info/WHEEL
qodex_dk-0.28.dist-info/top_level.txt
qodex_dk-0.28.dist-info/RECORD
