Metadata-Version: 2.1
Name: qodex-dk
Version: 0.28
Author: PunchyArchy
Author-email: ksmdrmvscthny@gmail.com
License-File: LICENSE
Requires-Dist: qsct
